cellbase/__init__.py
cellbase/cellbase.py
cellbase/celltable.py
cellbase/helper/__init__.py
cellbase/helper/helper.py
cellbase-0.1.2.dist-info/METADATA
cellbase-0.1.2.dist-info/RECORD
cellbase-0.1.2.dist-info/WHEEL
cellbase-0.1.2.dist-info/top_level.txt
