Metadata-Version: 2.1
Name: cellbase
Version: 0.1.2
Summary: Abstraction layer for accessing spreadsheet as database
Home-page: https://github.com/imjp94/cellbase
Author: imjp94
Author-email: imjp0921@gmail.com
License: MIT
Keywords: spreadsheet excel database query abstraction utility
Platform: UNKNOWN
Classifier: Development Status :: 3 - Alpha
Classifier: Topic :: Office/Business :: Financial :: Spreadsheet
Classifier: Topic :: Database
Classifier: Topic :: Utilities
Classifier: License :: OSI Approved :: MIT License
Requires-Dist: openpyxl
